azfunctionsmonitor/LoggingHelper.py
azfunctionsmonitor/__init__.py
azfunctionsmonitor-0.1.112.dist-info/LICENSE
azfunctionsmonitor-0.1.112.dist-info/WHEEL
azfunctionsmonitor-0.1.112.dist-info/METADATA
azfunctionsmonitor-0.1.112.dist-info/RECORD
