Metadata-Version: 2.1
Name: azfunctionsmonitor
Version: 0.1.112
Summary: Loging helper for Azure Monitor and Open Census
Home-page: https://github.com/cicorias/az-monitor-py-logging-pkg
License: Apache-2.0
Keywords: azure,monitor,cloud
Author: Shawn Cicoria
Author-email: github@cicoria.com
Requires-Python: >=3.7,<4.0
Classifier: License :: OSI Approved :: Apache Software License
Classifier: Programming Language :: Python :: 3
Classifier: Programming Language :: Python :: 3.7
Classifier: Programming Language :: Python :: 3.8
Classifier: Programming Language :: Python :: 3.9
Classifier: Topic :: Software Development :: Libraries :: Python Modules
Requires-Dist: azure-functions (>=1.6.0,<2.0.0)
Requires-Dist: opencensus-ext-azure (>=1.0.7,<2.0.0)
Project-URL: Documentation, https://github.com/cicorias/az-monitor-py-logging-pkg
